{
  "source": "R:\\Projects\\MOSDAC Help Bot\\Codes\\data_processing\\processed_output\\html\\www.mosdac.gov.in_calibration-reports.json",
  "text_entities": [
    {
      "text": "Satellite Data Archival Centre\nSkip",
      "label": "DATA_PRODUCT",
      "start": 42,
      "end": 77
    },
    {
      "text": "English",
      "label": "DATA_PRODUCT",
      "start": 115,
      "end": 122
    },
    {
      "text": "Satellite Data Archival Centre\nSpace Applications Centre",
      "label": "DATA_PRODUCT",
      "start": 154,
      "end": 210
    },
    {
      "text": "ISRO",
      "label": "ORG",
      "start": 212,
      "end": 216
    },
    {
      "text": "INSAT-3DR",
      "label": "SATELLITE",
      "start": 231,
      "end": 240
    },
    {
      "text": "INSAT-3D",
      "label": "SATELLITE",
      "start": 241,
      "end": 249
    },
    {
      "text": "SARAL",
      "label": "SATELLITE",
      "start": 284,
      "end": 289
    },
    {
      "text": "SCATSAT-1",
      "label": "SATELLITE",
      "start": 329,
      "end": 338
    },
    {
      "text": "AWS",
      "label": "DATA_PRODUCT",
      "start": 365,
      "end": 368
    },
    {
      "text": "RADAR",
      "label": "ORG",
      "start": 437,
      "end": 442
    },
    {
      "text": "DWR",
      "label": "ORG",
      "start": 444,
      "end": 447
    },
    {
      "text": "Global Ocean Current",
      "label": "DATA_PRODUCT",
      "start": 449,
      "end": 469
    },
    {
      "text": "Data Access",
      "label": "DATA_PRODUCT",
      "start": 470,
      "end": 481
    },
    {
      "text": "MT-SAPHIR",
      "label": "DATA_PRODUCT",
      "start": 529,
      "end": 538
    },
    {
      "text": "ISRO",
      "label": "STATION",
      "start": 590,
      "end": 594
    },
    {
      "text": "Indian Mainland Coastal Product",
      "label": "DATA_PRODUCT",
      "start": 785,
      "end": 816
    },
    {
      "text": "Renewable Energy\nCal-Val",
      "label": "ORG",
      "start": 901,
      "end": 925
    },
    {
      "text": "RSS Feeds",
      "label": "ORG",
      "start": 935,
      "end": 944
    },
    {
      "text": "Data Quality",
      "label": "DATA_PRODUCT",
      "start": 992,
      "end": 1004
    },
    {
      "text": "SCATSAT1",
      "label": "PRODUCT",
      "start": 1100,
      "end": 1108
    },
    {
      "text": "2017-11-03 15:29",
      "label": "DATE",
      "start": 1114,
      "end": 1130
    },
    {
      "text": "1",
      "label": "CARDINAL",
      "start": 1131,
      "end": 1132
    },
    {
      "text": "MOSDAC",
      "label": "ORG",
      "start": 1196,
      "end": 1202
    },
    {
      "text": "Space Applications Centre",
      "label": "ORG",
      "start": 1204,
      "end": 1229
    },
    {
      "text": "Indian Space Research Organisation",
      "label": "REGION",
      "start": 1231,
      "end": 1265
    },
    {
      "text": "Govt",
      "label": "ORG",
      "start": 1267,
      "end": 1271
    },
    {
      "text": "INDIA",
      "label": "REGION",
      "start": 1276,
      "end": 1281
    }
  ],
  "metadata_entities": [
    {
      "text": "Oceanographic Satellite Data Archival Centre",
      "label": "DATA_PRODUCT",
      "start": 19,
      "end": 63
    },
    {
      "text": "MOSDAC",
      "label": "DATA_PRODUCT",
      "start": 65,
      "end": 71
    },
    {
      "text": "Oceanographic Satellite Data Archival Centre",
      "label": "DATA_PRODUCT",
      "start": 19,
      "end": 63
    },
    {
      "text": "MOSDAC",
      "label": "DATA_PRODUCT",
      "start": 65,
      "end": 71
    },
    {
      "text": "a Data Centre of Space Applications Centre",
      "label": "DATA_PRODUCT",
      "start": 76,
      "end": 118
    },
    {
      "text": "MOSDAC",
      "label": "DATA_PRODUCT",
      "start": 212,
      "end": 218
    },
    {
      "text": "Indian",
      "label": "DATA_PRODUCT",
      "start": 274,
      "end": 280
    },
    {
      "text": "Oceanographic",
      "label": "DATA_PRODUCT",
      "start": 16,
      "end": 29
    },
    {
      "text": "Satellite",
      "label": "DATA_PRODUCT",
      "start": 31,
      "end": 40
    },
    {
      "text": "Data, Archival",
      "label": "DATA_PRODUCT",
      "start": 42,
      "end": 56
    },
    {
      "text": "Data Centre",
      "label": "DATA_PRODUCT",
      "start": 58,
      "end": 69
    },
    {
      "text": "MOSDAC",
      "label": "ORG",
      "start": 0,
      "end": 6
    }
  ]
}